pytoolsjps/__init__.py
pytoolsjps/postgres.py
pytoolsjps-0.0.7.dist-info/LICENSE.txt
pytoolsjps-0.0.7.dist-info/METADATA
pytoolsjps-0.0.7.dist-info/WHEEL
pytoolsjps-0.0.7.dist-info/top_level.txt
pytoolsjps-0.0.7.dist-info/RECORD
